<?xml version="1.0" encoding="UTF-8"?>
<odoo>
    <record id="record_comme_des_enfants" model="recording">
        <field name="name">September 28, 2009</field>
        <field name="ttype">sound</field>
        <field name="duration">2.8</field>
    </record>

    <record id="record_mistral_gagnant" model="recording">
        <field name="name">1986</field>
        <field name="ttype">sound</field>
        <field name="duration">2.78</field>
    </record>

    <record id="record_mistral_gagnant_2014" model="recording">
        <field name="name">Version 2014</field>
        <field name="ttype">sound</field>
        <field name="duration">3.06</field>
    </record>

    <record id="record_hotel_california_1977" model="recording">
        <field name="name">February 22, 1977</field>
        <field name="ttype">sound</field>
        <field name="duration">6.5</field>
    </record>

    <record id="record_money_for_nothing_album" model="recording">
        <field name="name">Album version</field>
        <field name="ttype">sound</field>
        <field name="duration">8.42</field>
    </record>
    <record id="record_money_for_nothing_vinyl" model="recording">
        <field name="name">Vinyl LP Edit</field>
        <field name="ttype">sound</field>
        <field name="duration">7.04</field>
    </record>
    <record id="record_money_for_nothing_single" model="recording">
        <field name="name">Official Single Edit</field>
        <field name="ttype">sound</field>
        <field name="duration">4.63</field>
    </record>
    <record id="record_money_for_nothing_single_promo" model="recording">
        <field name="name">Promo Single Edit</field>
        <field name="ttype">sound</field>
        <field name="duration">4.10</field>
    </record>

</odoo>
